MANIFEST.in
README.txt
setup.py
docs/HISTORY.txt
src/sphinxcontrib/__init__.py
src/sphinxcontrib.infrae.egg-info/PKG-INFO
src/sphinxcontrib.infrae.egg-info/SOURCES.txt
src/sphinxcontrib.infrae.egg-info/dependency_links.txt
src/sphinxcontrib.infrae.egg-info/namespace_packages.txt
src/sphinxcontrib.infrae.egg-info/not-zip-safe
src/sphinxcontrib.infrae.egg-info/requires.txt
src/sphinxcontrib.infrae.egg-info/top_level.txt
src/sphinxcontrib/infrae/__init__.py
src/sphinxcontrib/infrae/autointerface.py
src/sphinxcontrib/infrae/buildout.py