Metadata-Version: 1.0
Name: sphinxcontrib.infrae
Version: 1.0
Summary: Add-ons to sphinx to document Zope event and interfaces (and buildout configuration).
Home-page: http://infrae.com
Author: Infrae
Author-email: info@infrae.com
License: BSD
Keywords: sphinx color buildout zope interface
Platform: UNKNOWN
Classifier: License :: OSI Approved :: BSD License
Classifier: Programming Language :: Python
Classifier: Topic :: Software Development :: Libraries :: Python Modules
